saritasa_s3_tools/__init__.py
saritasa_s3_tools/async_client/__init__.py
saritasa_s3_tools/async_client/client.py
saritasa_s3_tools/client.py
saritasa_s3_tools/configs.py
saritasa_s3_tools/constants.py
saritasa_s3_tools/django/__init__.py
saritasa_s3_tools/django/drf_fields.py
saritasa_s3_tools/django/model_fields.py
saritasa_s3_tools/django/serializers.py
saritasa_s3_tools/django/shortcuts.py
saritasa_s3_tools/django/urls.py
saritasa_s3_tools/django/views.py
saritasa_s3_tools/factory.py
saritasa_s3_tools/keys.py
saritasa_s3_tools/py.typed
saritasa_s3_tools/testing/__init__.py
saritasa_s3_tools/testing/plugin.py
saritasa_s3_tools/testing/shortcuts.py
saritasa_s3_tools-0.6.0.dist-info/METADATA
saritasa_s3_tools-0.6.0.dist-info/WHEEL
saritasa_s3_tools-0.6.0.dist-info/entry_points.txt
saritasa_s3_tools-0.6.0.dist-info/licenses/LICENCE
saritasa_s3_tools-0.6.0.dist-info/RECORD
