Metadata-Version: 2.4
Name: saritasa-s3-tools
Version: 0.6.0
Summary: Tools For S3 Used By Saritasa
License: MIT
License-File: LICENCE
Keywords: python,aws,s3,boto3,django,drf
Author: Saritasa
Author-email: pypi@saritasa.com
Maintainer: Stanislav Khlud
Maintainer-email: stanislav.khlud@saritasa.com
Requires-Python: >=3.11,<4.0
Classifier: Development Status :: 4 - Beta
Classifier: Framework :: Django
Classifier: Framework :: Django :: 4.2
Classifier: Framework :: Django :: 5.0
Classifier: Framework :: Django :: 5.1
Classifier: Framework :: Django :: 5.2
Classifier: Framework :: Pytest
Classifier: Intended Audience :: Developers
Classifier: License :: OSI Approved :: MIT License
Classifier: Natural Language :: English
Classifier: Operating System :: OS Independent
Classifier: Programming Language :: Python :: 3
Classifier: Programming Language :: Python :: 3.11
Classifier: Programming Language :: Python :: 3.12
Classifier: Programming Language :: Python :: 3.13
Classifier: Programming Language :: Python :: 3.14
Classifier: Topic :: Software Development :: Libraries :: Python Modules
Provides-Extra: all
Provides-Extra: async
Provides-Extra: django
Provides-Extra: django-openapi
Provides-Extra: factory
Provides-Extra: testing
Requires-Dist: anyio (<5) ; extra == "async" or extra == "all"
Requires-Dist: boto3
Requires-Dist: boto3-stubs[s3]
Requires-Dist: django (<6) ; extra == "django" or extra == "all"
Requires-Dist: django-storages[boto3] (<2) ; extra == "django" or extra == "all"
Requires-Dist: djangorestframework (<4) ; extra == "django" or extra == "all"
Requires-Dist: drf-spectacular (<1) ; extra == "django-openapi" or extra == "all"
Requires-Dist: factory-boy (<4) ; extra == "factory" or extra == "all"
Requires-Dist: httpx (<1) ; extra == "testing" or extra == "all"
Requires-Dist: humanize (<5) ; extra == "django" or extra == "all"
Requires-Dist: pillow (<13) ; extra == "factory" or extra == "all"
Project-URL: Homepage, https://pypi.org/project/saritasa-s3-tools/
Project-URL: Repository, https://github.com/saritasa-nest/saritasa-s3-tools/
